klue
