Metadata-Version: 1.1
Name: klue-client-server
Version: 0.0.55
Summary: Swagger + Flask + Grequests + Bravado = Client/Server auto-spawning
Home-page: https://github.com/erwan-lemonnier/klue-client-server
Author: Erwan Lemonnier
Author-email: erwan@lemonnier.se
License: BSD
Platform: any
Classifier: Environment :: Web Environment
Classifier: Intended Audience :: Developers
Classifier: License :: OSI Approved :: BSD License
Classifier: Operating System :: OS Independent
Classifier: Programming Language :: Python
Classifier: Topic :: Internet :: WWW/HTTP :: Dynamic Content
Classifier: Topic :: Software Development :: Libraries :: Python Modules
